{
  "code": 200,
  "status": "OK",
  "data": {
    "number": 43,
    "name": "سُورَةُ الزُّخۡرُفِ",
    "englishName": "Az-Zukhruf",
    "englishNameTranslation": "Ornaments of gold",
    "revelationType": "Meccan",
    "numberOfAyahs": 89,
    "ayahs": [
      {
        "number": 4326,
        "text": "حا، ميم",
        "numberInSurah": 1,
        "juz": 25,
        "manzil": 6,
        "page": 489,
        "ruku": 424,
        "hizbQuarter": 196,
        "sajda": false
      },
      {
        "number": 4327,
        "text": "قسم دى، په دغه روښانه كتاب",
        "numberInSurah": 2,
        "juz": 25,
        "manzil": 6,
        "page": 489,
        "ruku": 424,
        "hizbQuarter": 196,
        "sajda": false
      },
      {
        "number": 4328,
        "text": "بېشكه مونږ دا عربي قرآن ګرځولى دى، د دې لپاره چې تاسو له عقل نه كار واخلئ",
        "numberInSurah": 3,
        "juz": 25,
        "manzil": 6,
        "page": 489,
        "ruku": 424,
        "hizbQuarter": 196,
        "sajda": false
      },
      {
        "number": 4329,
        "text": "او بېشكه دا په ام الكتب (لوح محفوظ) كې زمونږ په نزد خامخا ډېر اوچت، ډېر حكمت والا دى",
        "numberInSurah": 4,
        "juz": 25,
        "manzil": 6,
        "page": 489,
        "ruku": 424,
        "hizbQuarter": 196,
        "sajda": false
      },
      {
        "number": 4330,
        "text": "ایا نو مونږ له تاسو نه دا ذكر (قرآن) واړوو (بند كړو) بېخي اړول (بندول)، په دې سبب چې تاسو له حده تېرېدونكى قوم یئ",
        "numberInSurah": 5,
        "juz": 25,
        "manzil": 6,
        "page": 489,
        "ruku": 424,
        "hizbQuarter": 196,
        "sajda": false
      },
      {
        "number": 4331,
        "text": "او مونږ په ړومبنو خلقو كې څومره ډېر نبیان لېږلي دي",
        "numberInSurah": 6,
        "juz": 25,
        "manzil": 6,
        "page": 489,
        "ruku": 424,
        "hizbQuarter": 196,
        "sajda": false
      },
      {
        "number": 4332,
        "text": "او دوى ته به هېڅ یو نبي نه راته مګر دوى به په هغه پورې مسخرې كولې",
        "numberInSurah": 7,
        "juz": 25,
        "manzil": 6,
        "page": 489,
        "ruku": 424,
        "hizbQuarter": 196,
        "sajda": false
      },
      {
        "number": 4333,
        "text": "نو مونږ هغه هلاك كړل چې له دوى نه په نیولو (او قوت) كې ډېر زیات سخت وو او د ړومبنیو خلقو مثال (او حال) تېر شوى دى",
        "numberInSurah": 8,
        "juz": 25,
        "manzil": 6,
        "page": 489,
        "ruku": 424,
        "hizbQuarter": 196,
        "sajda": false
      },
      {
        "number": 4334,
        "text": "او قسم دى كه ته له دوى نه تپوس وكړې چې اسمانونه او ځمكه چا پیدا كړي دي (، نو) دوى به خامخا لازمًا ووايي چې دغه ډېر غالب، ډېر پوه ذات پیدا كړي دي",
        "numberInSurah": 9,
        "juz": 25,
        "manzil": 6,
        "page": 489,
        "ruku": 424,
        "hizbQuarter": 196,
        "sajda": false
      },
      {
        "number": 4335,
        "text": "هغه چې تاسو لپاره يې ځمكه فرش ګرځولې ده او تاسو لپاره يې په دې كې لارې پیدا كړي دي، د دې لپاره چې نېغه لار ومومئ",
        "numberInSurah": 10,
        "juz": 25,
        "manzil": 6,
        "page": 489,
        "ruku": 424,
        "hizbQuarter": 196,
        "sajda": false
      },
      {
        "number": 4336,
        "text": "او هغه ذات چې له بره نه يې اوبه په اندازې سره نازلې كړې دي، پس په دغو سره مونږ مړ ښار راژوندى كړى دى، همداسې به تاسو راوېستلى شئ",
        "numberInSurah": 11,
        "juz": 25,
        "manzil": 6,
        "page": 490,
        "ruku": 424,
        "hizbQuarter": 196,
        "sajda": false
      },
      {
        "number": 4337,
        "text": "او هغه ذات چې ټول قسمونه (انواع) يې پیدا كړي دي او تاسو لپاره يې له بېړیو او څارویو نه هغه پیدا كړي دي چې تاسو پرې سورېږئ",
        "numberInSurah": 12,
        "juz": 25,
        "manzil": 6,
        "page": 490,
        "ruku": 424,
        "hizbQuarter": 196,
        "sajda": false
      },
      {
        "number": 4338,
        "text": "د دې لپاره چې تاسو د هغو په شاګانو ښه برابر كېنئ، بیا د خپل رب نعمت رایاد كړئ، كله چې تاسو په دغه برابر كېنئ او ووایئ: پاكي ده هغه ذات لره چې زمونږ لپاره يې دا مسخر (او تابع) كړى دى۔ او مونږ ده لره په قابو كې راوستونكي نه یو",
        "numberInSurah": 13,
        "juz": 25,
        "manzil": 6,
        "page": 490,
        "ruku": 424,
        "hizbQuarter": 196,
        "sajda": false
      },
      {
        "number": 4339,
        "text": "او بېشكه مونږ خاص خپل رب ته خامخا بېرته ورتلونكي یو",
        "numberInSurah": 14,
        "juz": 25,
        "manzil": 6,
        "page": 490,
        "ruku": 424,
        "hizbQuarter": 196,
        "sajda": false
      },
      {
        "number": 4340,
        "text": "او دوى د ده په بنده ګانو كې ځينو لره د ده برخه (او اولاد) وګرځول، بېشكه انسان خامخا ډېر ښكاره ناشكره دى",
        "numberInSurah": 15,
        "juz": 25,
        "manzil": 6,
        "page": 490,
        "ruku": 424,
        "hizbQuarter": 196,
        "sajda": false
      },
      {
        "number": 4341,
        "text": "ایا (تاسو دا وایئ چې) هغه (الله) له هغه چا نه، چې دى يې پیدا كوي، د ځان لپاره لوڼه نیولي دي او تاسو يې په زامنو سره غوره كړي يئ",
        "numberInSurah": 16,
        "juz": 25,
        "manzil": 6,
        "page": 490,
        "ruku": 425,
        "hizbQuarter": 196,
        "sajda": false
      },
      {
        "number": 4342,
        "text": "حال دا چې كله دوى ته په هغه (لور) سره زېرى وركړى شي چې دى يې د رحمٰن لپاره مثال بیانوي (نو) د ده مخ تك تور شي، په دې حال كې چې دى له غمه ډك وي",
        "numberInSurah": 17,
        "juz": 25,
        "manzil": 6,
        "page": 490,
        "ruku": 425,
        "hizbQuarter": 196,
        "sajda": false
      },
      {
        "number": 4343,
        "text": "او ایا (دوى د الله لپاره مقرروي) هغه چې په كالیو (زیوراتو) كې لویه ولى شي، حال دا چې په جګړه كې خبره واضحه كوونكي نه وي",
        "numberInSurah": 18,
        "juz": 25,
        "manzil": 6,
        "page": 490,
        "ruku": 425,
        "hizbQuarter": 196,
        "sajda": false
      },
      {
        "number": 4344,
        "text": "او دوى (مشركان) ملايكو لره هغه چې دوى د رحمٰن بنده ګان دي، ښځې ګرځوي، ایا دوى د دغو پیدا كولو ته حاضر وو؟ یقینًا به د دوى ګواهي ولیكل شي او له دوى نه تپوس (هم) كېږي",
        "numberInSurah": 19,
        "juz": 25,
        "manzil": 6,
        "page": 490,
        "ruku": 425,
        "hizbQuarter": 196,
        "sajda": false
      },
      {
        "number": 4345,
        "text": "او دوى وايي: كه رحمٰن غوښتلي وى، (نو) مونږ به د دغو (باطلو معبودانو) عبادت نه وى كړى۔، دوى ته د دې (خبرې) هېڅ علم نشته، دوى يواځې اټكلونه چلوي",
        "numberInSurah": 20,
        "juz": 25,
        "manzil": 6,
        "page": 490,
        "ruku": 425,
        "hizbQuarter": 196,
        "sajda": false
      },
      {
        "number": 4346,
        "text": "ایا دوى ته مونږ له دغه (قرآن) نه مخكې كوم كتاب وركړى دى، پس دوى په هغه منګلولې ښخونكي دي",
        "numberInSurah": 21,
        "juz": 25,
        "manzil": 6,
        "page": 490,
        "ruku": 425,
        "hizbQuarter": 196,
        "sajda": false
      },
      {
        "number": 4347,
        "text": "بلكې دوى وايي: بېشكه مونږ خپل پلرونه په یوې لارې (طريقې) باندې موندلي دي، او بېشكه مونږ هم د دوى په قدمونو لاره موندونكي یو",
        "numberInSurah": 22,
        "juz": 25,
        "manzil": 6,
        "page": 490,
        "ruku": 425,
        "hizbQuarter": 196,
        "sajda": false
      },
      {
        "number": 4348,
        "text": "او همداسې مونږ له تا نه مخكې په كوم كلي كې هېڅ یو وېروونكى نه دى لېږلى مګر د هغه كلي متكبره مالدارو به وویل: بېشكه مونږ خپل پلرونه په یوه لاره (طريقه) موندلي دي او بېشكه مونږ هم د دوى په قدمونو اقتدا كوونكي یو",
        "numberInSurah": 23,
        "juz": 25,
        "manzil": 6,
        "page": 491,
        "ruku": 425,
        "hizbQuarter": 196,
        "sajda": false
      },
      {
        "number": 4349,
        "text": "(دوى ته به د دوى نبي) وویل: او ایا اګر كه ما تاسو ته له هغې (لارې) نه زیاته سمه لاره راوړې وي چې تاسو په هغې باندې خپل پلرونه موندلي دي؟ دوى به ویل: بېشكه مونږ په هغه (دین) كفر كوونكي یو چې تاسو په هغه سره رالېږل شوي يئ",
        "numberInSurah": 24,
        "juz": 25,
        "manzil": 6,
        "page": 491,
        "ruku": 425,
        "hizbQuarter": 197,
        "sajda": false
      },
      {
        "number": 4350,
        "text": "نو مونږ له دوى نه انتقام واخيست، نو ته وګوره د تكذیب كوونكو انجام څنګه و",
        "numberInSurah": 25,
        "juz": 25,
        "manzil": 6,
        "page": 491,
        "ruku": 425,
        "hizbQuarter": 197,
        "sajda": false
      },
      {
        "number": 4351,
        "text": "او (یاد كړه) هغه وخت چې ابراهیم خپل پلار او خپل قوم ته وویل: بېشكه زه له هغو (معبودانو) نه بېزاره یم چې تاسو يې عبادت كوئ",
        "numberInSurah": 26,
        "juz": 25,
        "manzil": 6,
        "page": 491,
        "ruku": 426,
        "hizbQuarter": 197,
        "sajda": false
      },
      {
        "number": 4352,
        "text": "غیر له هغه ذات نه چې زه يې پیدا كړى یم، پس یقینًا هغه به ما ته خامخا هدایت وكړي",
        "numberInSurah": 27,
        "juz": 25,
        "manzil": 6,
        "page": 491,
        "ruku": 426,
        "hizbQuarter": 197,
        "sajda": false
      },
      {
        "number": 4353,
        "text": "او هغه (ابراهیم) دغه (د توحید كلمه) په خپل اولاد كې باقي پاتې كېدونكې وګرځوله، د دې لپاره چې راوګرځي",
        "numberInSurah": 28,
        "juz": 25,
        "manzil": 6,
        "page": 491,
        "ruku": 426,
        "hizbQuarter": 197,
        "sajda": false
      },
      {
        "number": 4354,
        "text": "بلكې ما دوى او د دوى پلرونو ته نفع وركړه تر هغه پورې چې دوى ته حق (قرآن) او ښكاره بیانوونكى رسول راغى",
        "numberInSurah": 29,
        "juz": 25,
        "manzil": 6,
        "page": 491,
        "ruku": 426,
        "hizbQuarter": 197,
        "sajda": false
      },
      {
        "number": 4355,
        "text": "او كله چې دوى ته حق راغى دوى وویل: دا جادو دى، او بېشكه مونږ له ده نه انكار كوونكي یو",
        "numberInSurah": 30,
        "juz": 25,
        "manzil": 6,
        "page": 491,
        "ruku": 426,
        "hizbQuarter": 197,
        "sajda": false
      },
      {
        "number": 4356,
        "text": "او دوى وویل: دا قرآن په دوه كلیو (ښارونو) كې په یو غټ سړي ولې نه نازلاوه شي؟",
        "numberInSurah": 31,
        "juz": 25,
        "manzil": 6,
        "page": 491,
        "ruku": 426,
        "hizbQuarter": 197,
        "sajda": false
      },
      {
        "number": 4357,
        "text": "ایا دوى ستا د رب رحمت تقسیموي؟ مونږ د دوى په مینځ كې په دنيايي ژوند كې د دوى معشیت تقسیم كړى دى او په درجو كې مو د دوى ځینې د ځینو نورو له پاسه پورته كړي دي، د دې لپاره چې د دوى ځینې ځینې نور (تابع او) كار كوونكي ونيسي او ستا د رب رحمت له هغه نه ډېر غوره دى چې دوى يې جمع كوي",
        "numberInSurah": 32,
        "juz": 25,
        "manzil": 6,
        "page": 491,
        "ruku": 426,
        "hizbQuarter": 197,
        "sajda": false
      },
      {
        "number": 4358,
        "text": "او كه دا (خطره) نه وى چې خلق به ټول یوه ډله (كافران شي) نو مونږ به خامخا د هغه چا لپاره چې په رحمٰن كافران كېږي، د دوى كورونو ته به مو د سپینو زرو چتونه او داسې پوړۍ ګرځولې وى چې دوى به په هغو پاس ختلى",
        "numberInSurah": 33,
        "juz": 25,
        "manzil": 6,
        "page": 491,
        "ruku": 426,
        "hizbQuarter": 197,
        "sajda": false
      },
      {
        "number": 4359,
        "text": "او د دوى د كوټو لپاره به مو (د سپینو زرو) دروازې او تختونه جوړ كړي وى چې دوى به په هغو تكیه وهلې",
        "numberInSurah": 34,
        "juz": 25,
        "manzil": 6,
        "page": 492,
        "ruku": 426,
        "hizbQuarter": 197,
        "sajda": false
      },
      {
        "number": 4360,
        "text": "او له سرو زرو نه (دغه او نور زينتونه به مو وركړي وى) او نه دي دغه (ټول څیزونه) مګر د دنيايي ژوند سامان دى۔ او اخرت ستا د رب په نېز د متقیانو (پرهیزګارانو) لپاره دى",
        "numberInSurah": 35,
        "juz": 25,
        "manzil": 6,
        "page": 492,
        "ruku": 426,
        "hizbQuarter": 197,
        "sajda": false
      },
      {
        "number": 4361,
        "text": "او هر هغه څوك چې د رحمٰن له ذكر نه ځان ړوند كړي (، نو) مونږ به په ده باندې یو شیطان مسلط كړو، نو هغه به له ده سره تل ملګرى وي",
        "numberInSurah": 36,
        "juz": 25,
        "manzil": 6,
        "page": 492,
        "ruku": 427,
        "hizbQuarter": 197,
        "sajda": false
      },
      {
        "number": 4362,
        "text": "او بېشكه دغه (شیطانان) یقینًا دوى (خپل ملګري) له حقې لارې نه منع كوي او دوى ګمان كوي چې بېشكه دوى هدایت موندونكي دي",
        "numberInSurah": 37,
        "juz": 25,
        "manzil": 6,
        "page": 492,
        "ruku": 427,
        "hizbQuarter": 197,
        "sajda": false
      },
      {
        "number": 4363,
        "text": "تر هغه پورې چې كله دا مونږ ته راشي (نو) وايي به: اى كاشكې! زما په مینځ كې او ستا په مینځ كې د مشرق او مغرب هومره لرې والى وى، پس (دا) بد ملګرى دى",
        "numberInSurah": 38,
        "juz": 25,
        "manzil": 6,
        "page": 492,
        "ruku": 427,
        "hizbQuarter": 197,
        "sajda": false
      },
      {
        "number": 4364,
        "text": "او كله چې تاسو ظلم كړى دى (نو) تاسو ته به نن ورځ دا خبره له سره نفع درنـكړي چې بېشكه تاسو (او شیطانان ټول) په عذاب كې سره شریك یئ",
        "numberInSurah": 39,
        "juz": 25,
        "manzil": 6,
        "page": 492,
        "ruku": 427,
        "hizbQuarter": 197,
        "sajda": false
      },
      {
        "number": 4365,
        "text": "ایا نو ته به كڼو ته اورول وكړې، یا به ړندو ته لار ښوونه وكړې او هغه چا ته چې په ښكاره ګمراهۍ كې دى؟",
        "numberInSurah": 40,
        "juz": 25,
        "manzil": 6,
        "page": 492,
        "ruku": 427,
        "hizbQuarter": 197,
        "sajda": false
      },
      {
        "number": 4366,
        "text": "نو كه تا مونږ لازمًا بوځو، نو بېشكه مونږ له دوى نه انتقام اخيستونكي یو",
        "numberInSurah": 41,
        "juz": 25,
        "manzil": 6,
        "page": 492,
        "ruku": 427,
        "hizbQuarter": 197,
        "sajda": false
      },
      {
        "number": 4367,
        "text": "ایا مونږ تا ته خامخا هغه وښیو چې مونږ يې له دوى سره وعده كړې ده، نو بېشكه مونږ په دوى پوره قدرت لرونكي یو",
        "numberInSurah": 42,
        "juz": 25,
        "manzil": 6,
        "page": 492,
        "ruku": 427,
        "hizbQuarter": 197,
        "sajda": false
      },
      {
        "number": 4368,
        "text": "نو ته په هغه (قرآن) منګلې ولګوه چې تا ته وحي كړى شوى دى، بېشكه ته په نېغه لار يې",
        "numberInSurah": 43,
        "juz": 25,
        "manzil": 6,
        "page": 492,
        "ruku": 427,
        "hizbQuarter": 197,
        "sajda": false
      },
      {
        "number": 4369,
        "text": "او بېشكه دا (قرآن) تا لپاره او ستا د قوم لپاره ذكر (او نصیحت) دى۔ او ژر ده چې له تاسو نه به پوښتنه وكړى شي",
        "numberInSurah": 44,
        "juz": 25,
        "manzil": 6,
        "page": 492,
        "ruku": 427,
        "hizbQuarter": 197,
        "sajda": false
      },
      {
        "number": 4370,
        "text": "او ته زمونږ له هغو رسولانو نه تپوس وكړه چې مونږ له تا نه مخكې لېږلي دي۔، ایا مونږه له رحمن نه غیر نور معبودان مقرر كړي دي چې د دوى عبادت كولى شي",
        "numberInSurah": 45,
        "juz": 25,
        "manzil": 6,
        "page": 492,
        "ruku": 427,
        "hizbQuarter": 197,
        "sajda": false
      },
      {
        "number": 4371,
        "text": "او یقینًا یقینًا مونږ موسی زمونږ له نښو سره فرعون او د هغه سردارانو ته لېږلى و، پس ده وویل: بېشكه زه د رب العلمین رسول یم",
        "numberInSurah": 46,
        "juz": 25,
        "manzil": 6,
        "page": 492,
        "ruku": 428,
        "hizbQuarter": 197,
        "sajda": false
      },
      {
        "number": 4372,
        "text": "نو كله چې هغه دوى ته زمونږ په واضحو نښو سره راغى، ناڅاپه دوى په هغو (نښو) پورې خندل",
        "numberInSurah": 47,
        "juz": 25,
        "manzil": 6,
        "page": 492,
        "ruku": 428,
        "hizbQuarter": 197,
        "sajda": false
      },
      {
        "number": 4373,
        "text": "او مونږ به دوى ته هېڅ یوه نښه نه ښووله مګر چې هغه به د هغې له خور (مثل) نه ډېره لویه وه او مونږ دوى په عذاب سره راونیول، د دې لپاره چې دوى رجوع وكړي",
        "numberInSurah": 48,
        "juz": 25,
        "manzil": 6,
        "page": 493,
        "ruku": 428,
        "hizbQuarter": 197,
        "sajda": false
      },
      {
        "number": 4374,
        "text": "او دوى (فرعونیانو) وویل: اى جادوګره! (عالمه!) ته زمونږ لپاره له خپل رب نه دعا وغواړه، د هغې وعدې په سبب چې تا سره يې كړې ده۔، بېشكه مونږ خامخا هدایت موندونكي یو",
        "numberInSurah": 49,
        "juz": 25,
        "manzil": 6,
        "page": 493,
        "ruku": 428,
        "hizbQuarter": 197,
        "sajda": false
      },
      {
        "number": 4375,
        "text": "نو كله چې به مونږ له دوى نه عذاب لرې كړ، په هماغه وخت كې به دوى (وعده) ماتوله",
        "numberInSurah": 50,
        "juz": 25,
        "manzil": 6,
        "page": 493,
        "ruku": 428,
        "hizbQuarter": 197,
        "sajda": false
      },
      {
        "number": 4376,
        "text": "او فرعون په خپل قوم كې اواز وكړ، ويې ويل: اى زما قومه! ايا د مصر باچايي زما نه ده؟ او دغه ولې چې زما له لاندې بهېږي؟ ایا نو تاسو نه وینئ",
        "numberInSurah": 51,
        "juz": 25,
        "manzil": 6,
        "page": 493,
        "ruku": 428,
        "hizbQuarter": 197,
        "sajda": false
      },
      {
        "number": 4377,
        "text": "بلكې زه ډېر غوره یم له دغه (موسٰی) نه چې هغه سپك دى او نژدې نه دى چې خبره واضحه وكړي",
        "numberInSurah": 52,
        "juz": 25,
        "manzil": 6,
        "page": 493,
        "ruku": 428,
        "hizbQuarter": 197,
        "sajda": false
      },
      {
        "number": 4378,
        "text": "پس په ده باندې د سرو زرو بنګړي (وښي) ولې نه غورځول كېږي، یا له ده سره ملايك صف تړلي (پیوسته) ولې) نه راځي",
        "numberInSurah": 53,
        "juz": 25,
        "manzil": 6,
        "page": 493,
        "ruku": 428,
        "hizbQuarter": 197,
        "sajda": false
      },
      {
        "number": 4379,
        "text": "نو خپل قوم يې بې وقوفه وګرځاوه، نو دوى د ده خبره ومنله، بېشكه دوى فاسقان خلق وو",
        "numberInSurah": 54,
        "juz": 25,
        "manzil": 6,
        "page": 493,
        "ruku": 428,
        "hizbQuarter": 197,
        "sajda": false
      },
      {
        "number": 4380,
        "text": "نو كله چې دوى مونږ خفه كړو (، نو) مونږ له دوى نه انتقام واخيست، پس مونږه دوى ټول غرق كړل",
        "numberInSurah": 55,
        "juz": 25,
        "manzil": 6,
        "page": 493,
        "ruku": 428,
        "hizbQuarter": 197,
        "sajda": false
      },
      {
        "number": 4381,
        "text": "نومونږ دوى پیشوایان او مثال وګرځول د وروستنیو خلقو لپاره",
        "numberInSurah": 56,
        "juz": 25,
        "manzil": 6,
        "page": 493,
        "ruku": 428,
        "hizbQuarter": 197,
        "sajda": false
      },
      {
        "number": 4382,
        "text": "او كله چې د مریمې زوى د مثال په طور بیان كړى شو، (نو) ناڅاپه ستا قوم د دغه (مثال) پورې (له خوشالۍ نه) چغې وهلې",
        "numberInSurah": 57,
        "juz": 25,
        "manzil": 6,
        "page": 493,
        "ruku": 429,
        "hizbQuarter": 198,
        "sajda": false
      },
      {
        "number": 4383,
        "text": "او ويې ويل: ایا زمونږ معبودان غوره دي، یا كه هغه؟ دوى تا ته دا (مثال) بیان نه كړ مګر د جګړې لپاره۔ بلكې دوى ډېر جګړه كوونكى قوم دى",
        "numberInSurah": 58,
        "juz": 25,
        "manzil": 6,
        "page": 493,
        "ruku": 429,
        "hizbQuarter": 198,
        "sajda": false
      },
      {
        "number": 4384,
        "text": "دغه نه دى مګر یو بنده دى چې مونږ په ده انعام كړى دى او د بني اسرائیلو لپاره مو هغه (د قدرت) یو مثال ګرځولى و",
        "numberInSurah": 59,
        "juz": 25,
        "manzil": 6,
        "page": 493,
        "ruku": 429,
        "hizbQuarter": 198,
        "sajda": false
      },
      {
        "number": 4385,
        "text": "او كه مونږ غوښتلي وى (نو) مونږ به ستاسو په ځاى په ځمكه كې ملايك پیدا كړي وى، چې خلیفګان شوي به وى",
        "numberInSurah": 60,
        "juz": 25,
        "manzil": 6,
        "page": 493,
        "ruku": 429,
        "hizbQuarter": 198,
        "sajda": false
      },
      {
        "number": 4386,
        "text": "او بېشكه دغه (عیسٰی) د قیامت لپاره یقینًا یوه لویه نښه ده، نو تاسو د دغه (قیامت) په باره كې له سره شك مه كوئ۔، دا نېغه لار ده",
        "numberInSurah": 61,
        "juz": 25,
        "manzil": 6,
        "page": 494,
        "ruku": 429,
        "hizbQuarter": 198,
        "sajda": false
      },
      {
        "number": 4387,
        "text": "او شیطان دې تا (له دې نېغې لارې نه) له سره وا نه ړوي، بېشكه هغه تاسو لپاره ښكاره دښمن دى",
        "numberInSurah": 62,
        "juz": 25,
        "manzil": 6,
        "page": 494,
        "ruku": 429,
        "hizbQuarter": 198,
        "sajda": false
      },
      {
        "number": 4388,
        "text": "او كله چې عيسٰى له ښكاره دلیلونو سره راغى، ويې ويل: (اى بني اسرائیلو!) یقینًا ما تاسو ته حكم راوړى دى او د دې لپاره (راغلى یم) چې تاسو ته ځینې هغه (احكام) بیان كړم چې تاسو په هغو كې اختلاف كوئ، نو تاسو له الله نه ووېرېږئ او زما اطاعت وكړئ",
        "numberInSurah": 63,
        "juz": 25,
        "manzil": 6,
        "page": 494,
        "ruku": 429,
        "hizbQuarter": 198,
        "sajda": false
      },
      {
        "number": 4389,
        "text": "بېشكه هم دا الله زما رب دى او ستاسو رب دى، لهٰذا تاسو د ده عبادت كوئ۔، دغه نېغه لاره ده",
        "numberInSurah": 64,
        "juz": 25,
        "manzil": 6,
        "page": 494,
        "ruku": 429,
        "hizbQuarter": 198,
        "sajda": false
      },
      {
        "number": 4390,
        "text": "نو (د نصرانیانو) دغه ډلې په خپل منیځ كې سره مختلفې شوې، نو د هغو كسانو لپاره چې ظلم يې كړى دى، د ډېرې دردوونكي ورځې له عذاب نه هلاكت دى",
        "numberInSurah": 65,
        "juz": 25,
        "manzil": 6,
        "page": 494,
        "ruku": 429,
        "hizbQuarter": 198,
        "sajda": false
      },
      {
        "number": 4391,
        "text": "دوى انتظار نه كوي مګر د قیامت چې په دوى به ناڅاپه راشي، او دوى به نه پوهېږي",
        "numberInSurah": 66,
        "juz": 25,
        "manzil": 6,
        "page": 494,
        "ruku": 429,
        "hizbQuarter": 198,
        "sajda": false
      },
      {
        "number": 4392,
        "text": "په دغې ورځ كې به خواږه یاران، د دوى ځینې به د ځینو نورو دښمنان وي۔، غیر له متقیانو نه",
        "numberInSurah": 67,
        "juz": 25,
        "manzil": 6,
        "page": 494,
        "ruku": 429,
        "hizbQuarter": 198,
        "sajda": false
      },
      {
        "number": 4393,
        "text": "اى زما بنده ګانو! نن ورځ په تاسو وېره نشته او نه به تاسو غمژن كېږئ",
        "numberInSurah": 68,
        "juz": 25,
        "manzil": 6,
        "page": 494,
        "ruku": 430,
        "hizbQuarter": 198,
        "sajda": false
      },
      {
        "number": 4394,
        "text": "هغه كسان چې زمونږ په ایتونو يې ایمان راوړى دى او دوى مسلمانان وو",
        "numberInSurah": 69,
        "juz": 25,
        "manzil": 6,
        "page": 494,
        "ruku": 430,
        "hizbQuarter": 198,
        "sajda": false
      },
      {
        "number": 4395,
        "text": "(دوى ته به ویلى شي:) تاسو جنت ته ننوځئ، تاسو او ستاسو ښځې، تاسو به خوشالولى شئ",
        "numberInSurah": 70,
        "juz": 25,
        "manzil": 6,
        "page": 494,
        "ruku": 430,
        "hizbQuarter": 198,
        "sajda": false
      },
      {
        "number": 4396,
        "text": "په دوى به كاسې د سرو زرو او ګلاسونه ګرځول كېږي او په دغو (جنتونو) كې به هغه څه وي چې نفسونه (زړونه) د هغو خواهش كوي او سترګې (پرې) خوند اخلي۔ او تاسو به په دغو كې تل ترتله یئ",
        "numberInSurah": 71,
        "juz": 25,
        "manzil": 6,
        "page": 494,
        "ruku": 430,
        "hizbQuarter": 198,
        "sajda": false
      },
      {
        "number": 4397,
        "text": "او دغه هغه جنتونه دي چې تاسو ته د هغو عملونو په سبب په میراث كې دركړى شول چې تاسو به كول",
        "numberInSurah": 72,
        "juz": 25,
        "manzil": 6,
        "page": 494,
        "ruku": 430,
        "hizbQuarter": 198,
        "sajda": false
      },
      {
        "number": 4398,
        "text": "تاسو لپاره په دغو كې ډېرې مېوې دي چې تاسو به له هغو ځنې خوراك كوئ",
        "numberInSurah": 73,
        "juz": 25,
        "manzil": 6,
        "page": 494,
        "ruku": 430,
        "hizbQuarter": 198,
        "sajda": false
      },
      {
        "number": 4399,
        "text": "بېشكه مجرمان به د جهنم په عذاب كې تل پاتې كېدونكي وي",
        "numberInSurah": 74,
        "juz": 25,
        "manzil": 6,
        "page": 495,
        "ruku": 430,
        "hizbQuarter": 198,
        "sajda": false
      },
      {
        "number": 4400,
        "text": "چې دغه (عذاب) به له دوى څخه نه كمولى شي او دوى به په دغه (عذاب) كې نا امېده اوسي",
        "numberInSurah": 75,
        "juz": 25,
        "manzil": 6,
        "page": 495,
        "ruku": 430,
        "hizbQuarter": 198,
        "sajda": false
      },
      {
        "number": 4401,
        "text": "او مونږ په دوى ظلم نه دى كړى او لېكن هم دوى پخپله ظالمان وو",
        "numberInSurah": 76,
        "juz": 25,
        "manzil": 6,
        "page": 495,
        "ruku": 430,
        "hizbQuarter": 198,
        "sajda": false
      },
      {
        "number": 4402,
        "text": "او دغه (دوزخیان) به اواز وكړي: اى مالكه! ستا رب دې مونږ مړه كړي، هغه (مالك) به ووايي: بېشكه تاسو (تل) ژوندي پاتې كېدونكي یئ",
        "numberInSurah": 77,
        "juz": 25,
        "manzil": 6,
        "page": 495,
        "ruku": 430,
        "hizbQuarter": 198,
        "sajda": false
      },
      {
        "number": 4403,
        "text": "یقینًا یقینًا مونږ تاسو ته حق راوړى و او لېكن ستاسو زیاتره حق لره بدګڼونكي دي",
        "numberInSurah": 78,
        "juz": 25,
        "manzil": 6,
        "page": 495,
        "ruku": 430,
        "hizbQuarter": 198,
        "sajda": false
      },
      {
        "number": 4404,
        "text": "ایا بلكې دوى د یو كار پخه اراده كړې ده۔، نو بېشكه مونږ (هم) خپل (تدبیر) محكم كوونكي یو",
        "numberInSurah": 79,
        "juz": 25,
        "manzil": 6,
        "page": 495,
        "ruku": 430,
        "hizbQuarter": 198,
        "sajda": false
      },
      {
        "number": 4405,
        "text": "ایا دوى دا ګمان كوي چې بېشكه مونږ د دوى پټې خبرې او پټې مشورې نه اورو، ولې نه! او زمونږ رسولان ليكل كوي د دوى ترڅنګه",
        "numberInSurah": 80,
        "juz": 25,
        "manzil": 6,
        "page": 495,
        "ruku": 430,
        "hizbQuarter": 198,
        "sajda": false
      },
      {
        "number": 4406,
        "text": "ته (دوى ته) ووایه: كه چېرې د رحمٰن لپاره اولاد وى، نو زه به (د هغه) ترټولو اول عبادت كوونكى وم",
        "numberInSurah": 81,
        "juz": 25,
        "manzil": 6,
        "page": 495,
        "ruku": 430,
        "hizbQuarter": 198,
        "sajda": false
      },
      {
        "number": 4407,
        "text": "پاكي ده د اسمانونو او ځمكې رب لره، د عرش رب لره له هغه څه نه چې دوى يې (د هغه په باره كې) بیانوي",
        "numberInSurah": 82,
        "juz": 25,
        "manzil": 6,
        "page": 495,
        "ruku": 430,
        "hizbQuarter": 198,
        "sajda": false
      },
      {
        "number": 4408,
        "text": "نو ته دوى پرېږده چې (په باطلو خبرو كې) غوټې وهي او لوبې كوي تر هغه پورې چې دوى د خپلې هغې ورځې سره ملاقات وكړي چې دوى ته به يې وعده وركولى شوه",
        "numberInSurah": 83,
        "juz": 25,
        "manzil": 6,
        "page": 495,
        "ruku": 430,
        "hizbQuarter": 198,
        "sajda": false
      },
      {
        "number": 4409,
        "text": "او هم دى هغه دى ذات چې په اسمان كې معبود دى او په ځمكه كې (هم) معبود دى، او هم دى ډېر حكمت والا، ښه پوه دى",
        "numberInSurah": 84,
        "juz": 25,
        "manzil": 6,
        "page": 495,
        "ruku": 430,
        "hizbQuarter": 198,
        "sajda": false
      },
      {
        "number": 4410,
        "text": "او ډېر بركت ناك دى هغه ذات چې خاص د هغه لپاره د اسمانونو او ځمكې باچايي ده او د هغه څه چې د دغو دواړو په مينځ كې دي او خاص له هغه سره د قیامت د علم دى او خاص هغه ته به تاسو بېرته بېولى شئ",
        "numberInSurah": 85,
        "juz": 25,
        "manzil": 6,
        "page": 495,
        "ruku": 430,
        "hizbQuarter": 198,
        "sajda": false
      },
      {
        "number": 4411,
        "text": "او هغه معبودان چې دوى يې له دغه (الله) نه غیر بلي؛ د شفاعت هېڅ اختیار نه لري، مګر هغه څوك چې د حق ګواهي يې وركړې وي، په دې حال كې چې دوى پوهېږي",
        "numberInSurah": 86,
        "juz": 25,
        "manzil": 6,
        "page": 495,
        "ruku": 430,
        "hizbQuarter": 198,
        "sajda": false
      },
      {
        "number": 4412,
        "text": "او قسم دى كه ته له دوى نه تپوس وكړې چې دوى چا پیدا كړي دي (نو) دوى به خامخا ضرور ووايي: الله (پیدا كړي دي) نو كوم طرف ته دوى ګرځول كېږي؟",
        "numberInSurah": 87,
        "juz": 25,
        "manzil": 6,
        "page": 495,
        "ruku": 430,
        "hizbQuarter": 198,
        "sajda": false
      },
      {
        "number": 4413,
        "text": "او قسم دى د دغه (رسول) په دې وینا چې اى زما ربه! بېشكه زما دا قوم ایمان نه راوړي",
        "numberInSurah": 88,
        "juz": 25,
        "manzil": 6,
        "page": 495,
        "ruku": 430,
        "hizbQuarter": 198,
        "sajda": false
      },
      {
        "number": 4414,
        "text": "نو ته له دوى نه مخ وګرځوه او ووایه: سلام۔، پس ژر به دوى پوه شي",
        "numberInSurah": 89,
        "juz": 25,
        "manzil": 6,
        "page": 495,
        "ruku": 430,
        "hizbQuarter": 198,
        "sajda": false
      }
    ],
    "edition": {
      "identifier": "ps.abdulwali",
      "language": "ps",
      "name": "عبدالولي",
      "englishName": "عبدالولي",
      "format": "text",
      "type": "translation",
      "direction": "rtl"
    }
  }
}